matrixutils/__init__.py
matrixutils/_version.py
matrixutils/add.py
matrixutils/matmul.py
matrixutils/transpose.py
matrixutils_example_pkg-0.0.6.dist-info/licenses/LICENSE
matrixutils_example_pkg-0.0.6.dist-info/METADATA
matrixutils_example_pkg-0.0.6.dist-info/WHEEL
matrixutils_example_pkg-0.0.6.dist-info/top_level.txt
matrixutils_example_pkg-0.0.6.dist-info/RECORD
