Metadata-Version: 2.4
Name: matrixutils_example_pkg
Version: 0.0.6
Summary: Matrix utilities example package
Requires-Python: >=3.8
License-File: LICENSE
Dynamic: license-file
